{"category": "NATURE", "comments": "", "clues": [{"answer": ["Poisonous"], "question": "The spots on a spotted salamander are a warning to predators that the salamander is this"}, {"answer": ["Beat its wings"], "question": "A bee does it about 200 times a second; a mosquito, 500 times a second"}, {"answer": ["Plant kingdom"], "question": "This kingdom is commonly divided into vascular, including cycads, & nonvascular, including hornworts"}, {"answer": ["Spiral"], "question": "The whelk, a carnivorous marine gastropod, has a shell of this shape"}, {"answer": ["Starch"], "question": "In a popular science experiment iodine on a piece of potato turns it dark, indicating this substance is present"}]}
{"category": "CAR MODELS", "comments": "", "clues": [{"answer": ["Buick"], "question": "Regal,Riviera,LeSabre"}, {"answer": ["Volkswagen"], "question": "Passat,Golf,Jetta"}, {"answer": ["Isuzu"], "question": "Amigo,Rodeo,Trooper"}, {"answer": ["Porsche"], "question": "550 Spyder,Boxster,944"}, {"answer": ["Audi"], "question": "5000,A4,A8"}]}
{"category": "THE QUOTABLE JOHN ADAMS", "comments": "", "clues": [{"answer": ["Vice president"], "question": "In 1793 Adams said of it, \"My country has in its wisdom contrived for me the most insignificant office\""}, {"answer": ["Thomas Jefferson"], "question": "\"You and I ought not to die before we have explained ourselves to each other\", Adams wrote him years before July 4, 1826"}, {"answer": ["Abigail Adams"], "question": "In 1779 Adams wrote to her, \"I must not write a word to you about politics, because you are a woman\""}, {"answer": ["Boston Massacre"], "question": "\"Facts are stubborn things\", Adams said in defense of British soldiers involved in this 1770 clash"}, {"answer": ["Government"], "question": "Adams wished for one \"Of laws, and not of man\", but felt that \"fear is the foundation of most\""}]}
{"category": "WOMEN", "comments": "", "clues": [{"answer": ["Pocahontas"], "question": "On a 1616 trip to England, she had a touching reunion with John Smith"}, {"answer": ["Revlon"], "question": "Cindy Crawford is one of \"The Most Unforgettable Women in the World\" who wear this makeup brand"}, {"answer": ["Sonja Henie"], "question": "(Hi, I'm Tara Lipinski [\"World Class Skater\"])  In 1998 I broke a 70-year-old record when I replaced her as the youngest Olympic figure skating champ ever"}, {"answer": ["Ally Sheedy"], "question": "Once a member of the \"Brat Pack\", she returned to the big screen as a heroin-addicted photographer in 1998's \"High Art\""}, {"answer": ["Ima Hogg"], "question": "This unfortunately named woman who founded the Houston Symphony never had a sister named Ura Hogg"}]}
{"category": "\"SO\" WHAT?", "comments": "", "clues": [{"answer": ["Soprano"], "question": "Leontyne Price, Beverly Sills, or their singing voice"}, {"answer": ["Soliloquy"], "question": "It's a speech given by a character in a play while alone -- \"To Be or Not to Be\", for example"}, {"answer": ["Sophisticated"], "question": "Elegant & refined, like Duke Ellington's \"Lady\""}, {"answer": ["Solarium"], "question": "It's a glassed-in room or gallery where you can catch some rays"}, {"answer": ["Somalia"], "question": "In 1992 supermodel Iman returned to this country of her birth for a documentary on the famine there"}]}
{"category": "CDs", "comments": "", "clues": [{"answer": ["Michael Jackson"], "question": "\"Billie Jean\" & \"Beat It\" are part of his \"HIStory\", a 1995 collection"}, {"answer": ["\"Bedtime Stories\""], "question": "Madonna told these \"stories\" on a 1994 CD"}, {"answer": ["Simon & Garfunkel"], "question": "On the cover of this duet's boxed set \"Old Friends\", a cigarette has been airbrushed out of Paul's fingers"}, {"answer": ["\"Nevermind\""], "question": "On a Nirvana CD, this title follows the words \"Oh well, whatever...\""}, {"answer": ["Depeche Mode"], "question": "\"Personal Jesus\" & \"Enjoy the Silence\" are on a 1998 compilation by this English band with a French name"}]}
{"category": "JIM CLASS", "comments": "", "clues": [{"answer": ["Jim Henson"], "question": "As Kermit could tell you, this man created \"Fraggle Rock\" too"}, {"answer": ["Jim Backus"], "question": "He was \"Mr. Magoo\" as well as Thurston Howell III"}, {"answer": ["James Joyce"], "question": "In 1918 this Irish author penned in a letter, \"Writing in English is the most ingenious torture ever devised...\""}, {"answer": ["James (Jim) West"], "question": "This \"Wild Wild\" character played by Robert Conrad was partnered with Artemus Gordon on '60s TV"}, {"answer": ["Jimmy Doolittle"], "question": "Despite his name, this man did quite a lot in leading a bombing raid over Tokyo in April 1942"}]}
{"category": "NEVER HEARD OF IT BEFORE", "comments": "", "clues": [{"answer": ["Hope"], "question": "In 1992 Bill Clinton said, \"I still believe in a place called\" this, his Arkansas hometown"}, {"answer": ["Afrikaans"], "question": "In 1976 Soweto, near Johnannesburg, was the site of protests against the forced use of this language"}, {"answer": ["Kosovo"], "question": "Fighting broke out in 1998 in this Serbian-ruled province that's 90% ethnic Albanian"}, {"answer": ["(Mainland) China"], "question": "In 1958 the islands of Quemoy & Matsu in the Formosa Strait were bombarded by this country"}, {"answer": ["Iraq"], "question": "Arbil, designated the capital of the Kurds, was seized by this country's troops in 1996"}]}
{"category": "FEMALE FILM ROLES", "comments": "", "clues": [{"answer": ["Julie Andrews"], "question": "\"Victor/Victoria\"(1982)"}, {"answer": ["Daryl Hannah"], "question": "\"Roxanne\"(1987)"}, {"answer": ["Sharon Stone"], "question": "\"Gloria\"(1999)"}, {"answer": ["Gena Rowlands"], "question": "\"Gloria\"(1980)"}, {"answer": ["Nastassja Kinski"], "question": "\"Tess\"(1979)"}]}
{"category": "BAN THAT BOOK!", "comments": "", "clues": [{"answer": ["\"Leaves of Grass\""], "question": "Threats of prosecution for the use of explicit language delayed an 1881 edition of this Walt Whitman collection"}, {"answer": ["\"Candide\""], "question": "In 1929 U.S. Customs officials seized copies of this satiric Voltaire novel bound for Harvard"}, {"answer": ["Myanmar"], "question": "The government of this country, AKA Burma, has banned all translations of the Bible into local languages"}, {"answer": ["\"Fannie Hill\""], "question": "AKA the \"Memoirs of a Woman of Pleasure\", this 1749 John Cleland work has been frequently suppressed"}, {"answer": ["Comstock Law"], "question": "\"The Canterbury Tales\" & \"The Arabian Nights\" were banned for decades from U.S. mails under this 1873 law"}]}
