{"category": "OPERA", "comments": "", "clues": [{"answer": ["\"Don Quixote\""], "question": "\"Master Peter's Puppet Show\" -- a puppet opera (?!) -- is based on a passage from this Cervantes work"}, {"answer": ["Richard Wagner"], "question": "The composition of this German's \"Ring\" cycle spanned over 20 years"}, {"answer": ["\"Aida\""], "question": "An Ethiopian slave girl is torn between love & patriotism in the Egypt of the Pharaohs in this Verdi opera"}, {"answer": ["W.A. Mozart"], "question": "Operas by this composer include \"Cosi fan tutte\" & \"The Magic Flute\""}, {"answer": ["\"The Clowns\""], "question": "It's the English title of the opera \"I Pagliacci\" & the name of a ballet that juxtaposes terror & buffoonery"}]}
{"category": "KNOWN BY THEIR INITIALS", "comments": "", "clues": [{"answer": ["k.d. lang"], "question": "Singer kathryn dawn..."}, {"answer": ["L.L. Bean"], "question": "Maine retailer Leon Leonwood..."}, {"answer": ["H.L. Mencken"], "question": "Journalist & essayist Henry Louis..."}, {"answer": ["Y.A. Tittle"], "question": "NFL All-Pro Yelberton Abraham..."}, {"answer": ["W.E.B. Du Bois"], "question": "Social reformer William Edward Burghardt..."}]}
{"category": "BILL TO LAW", "comments": "", "clues": [{"answer": ["Clerk"], "question": "For the first reading, the representative or senator gives the bill to the person in this post"}, {"answer": ["Committee"], "question": "After the first reading, the bill is sent to one of these that may table it"}, {"answer": ["Roll call"], "question": "On the third reading, the bill is put either to a voice vote or this alphabetical vote"}, {"answer": ["2/3"], "question": "This fraction of the House needs to vote yes to overturn a presidential veto"}, {"answer": ["10"], "question": "If Congress adjourns, a president can veto a bill by not signing it within this many days (Sundays excluded)"}]}
{"category": "HILLARY & JACKIE", "comments": "(Alex: We're talking about the first ladies here, not the film.)", "clues": [{"answer": ["Rodham & Bouvier"], "question": "Their maiden names"}, {"answer": ["Photographer"], "question": "Hillary first dated Bill while a law student & Jackie first dated John while she was the \"inquiring\" one of these for a paper"}, {"answer": ["Caroline"], "question": "Hillary had Chelsea in 1980 & Jackie had this child in 1957"}, {"answer": ["Wellesley"], "question": "Jackie earned her B.A. from George Washington University & Hillary graduated from this college in 1969"}, {"answer": ["Doubleday"], "question": "Hillary's \"It Takes A Village\" was published by Simon & Schuster; Jackie worked for this other NYC book publisher"}]}
{"category": "THE FORGOTTEN MARX BROTHERS", "comments": "", "clues": [{"answer": ["Tango"], "question": "We won't be surprised if \"it takes two to\" name this brother who loved a certain Latin-American dance"}, {"answer": ["Wino"], "question": "You might find this brother in the cellar swigging from a bottle of Muscatel"}, {"answer": ["Klepto"], "question": "This brother whose nickname included \"Maniac\" was named for his irresistable impulse to steal"}, {"answer": ["Sterno"], "question": "This brother's name, a trademark, comes from always carrying a can of flammable jelly to heat up food"}, {"answer": ["Gonzo"], "question": "Few remember this brother who got his name by practicing the same kind of journalism as Hunter Thompson"}]}
{"category": "MONGOLIA", "comments": "", "clues": [{"answer": ["Goats"], "question": "One of Mongolia's main occupations is raising these animals to produce cashmere"}, {"answer": ["Truth"], "question": "The name of Mongolia's Communist Party newspaper Unen, like Russia's Pravda, means this"}, {"answer": ["\"Contract with Mongolia\""], "question": "The 1996 election was won using a platform called this, in imitation of the USA's Republicans in 1994"}, {"answer": ["Genghis Khan"], "question": "The ruined city of Karakorum is where this conqueror established his headquarters in 1220"}, {"answer": ["Shaman"], "question": "Like Native Americans, many Mongolians follow this type of mystic healer whose name means \"he who knows\""}]}
{"category": "THE DIRECTOR'S CHAIR", "comments": "", "clues": [{"answer": ["Woody Allen"], "question": "\"Crimes and Misdemeanors\",\"Hannah and Her Sisters\""}, {"answer": ["George Lucas"], "question": "\"THX 1138\",\"American Graffiti\""}, {"answer": ["Paul Verhoeven"], "question": "\"RoboCop\",\"Basic Instinct\",\"Starship Troopers\""}, {"answer": ["Sam Raimi"], "question": "\"Crimewave\",\"The Quick and the Dead\",\"Evil Dead II\""}, {"answer": ["Terrence Malick"], "question": "\"Badlands\",\"Days of Heaven\",\"The Thin Red Line\""}]}
{"category": "ASTRONOMERS", "comments": "", "clues": [{"answer": ["Moon"], "question": "Galileo's first discovery in 1609 was that the surface of this is not smooth, but pitted"}, {"answer": ["Edmond Halley"], "question": "He predicted a comet he observed in 1682 would return in 1758 (he was right)"}, {"answer": ["Galaxy"], "question": "Edwin Hubble was the first to say the Andromeda nebula was one of these, separate from ours"}, {"answer": ["Nicolaus Copernicus"], "question": "Aristarchos proposed a heliocentric theory about 1,700 years before this famous Pole"}, {"answer": ["Pulsar"], "question": "In 1967 Jocelyn Bell Burnell discovered this new type of star that emits regular bursts of radio waves"}]}
{"category": "SAVE THE PRINCE OF WALES", "comments": "", "clues": [{"answer": ["Polo"], "question": "At Cambridge Charles got his university colors in this sport"}, {"answer": ["Camilla Parker Bowles"], "question": "On January 28, 1999 Prince Charles made his first public appearance with this woman; it was at a party for her sister"}, {"answer": ["Royal Shakespeare Company"], "question": "As president of the RSC, this group, Charles probably knows not to say the name of \"the Scottish play\""}, {"answer": ["Britannia"], "question": "Charles honeymooned on this royal yacht that no longer rules the waves; it's been retired"}, {"answer": ["Cornwall"], "question": "The prince gets no money from the state; he earns about 5 million pounds yearly from the duchy of this"}]}
{"category": "1900", "comments": "", "clues": [{"answer": ["Sigmund Freud"], "question": "He published \"The Interpretation of Dreams\""}, {"answer": ["Ferdinand von Zeppelin"], "question": "His first airship took flight near Friedrichshafen, Germany on July 2, 1900"}, {"answer": ["Boers"], "question": "The Boxers were rebelling in China & the British were fighting this group in South Africa"}, {"answer": ["Tennis"], "question": "In February Dwight F. Davis donated a silver cup to this sport"}, {"answer": ["William Jennings Bryan"], "question": "The Populists met in May 1900 in South Dakota to nominate this man for president"}]}
{"category": "BE MY \"PAL\"", "comments": "", "clues": [{"answer": ["Palestine"], "question": "Under a League of Nations mandate, the British oversaw the affairs of this region from 1920 to 1948"}, {"answer": ["Palate"], "question": "It can mean the roof of the mouth, or more generally the sense of taste"}, {"answer": ["Palette"], "question": "A board on which a painter mixes colors, or the range of colors he uses"}, {"answer": ["Palisade"], "question": "A fence of stakes forming a defensive barrier or fortification"}, {"answer": ["Paladins"], "question": "These heroic champions of chivalry share their name with a 1950s Richard Boone TV character"}]}
