{"category": "PASS THE DUCHY", "comments": "", "clues": [{"answer": ["Herzegovina"], "question": "The name of this partner of Bosnia means \"independent duchy\""}, {"answer": ["Dijon"], "question": "Around 1015 it cut the mustard to be named capital of the duchy of Burgundy"}, {"answer": ["Eleanor"], "question": "In 1137 she inherited the duchy of Aquitaine & married Louis VII"}, {"answer": ["Belgium"], "question": "The area of the duchy of Brabant is split today between the Netherlands & this country"}, {"answer": ["Luxembourg"], "question": "The European Investment Bank is headquartered in this grand duchy"}]}
{"category": "CLOWNS", "comments": "", "clues": [{"answer": ["The Howdy Doody Show"], "question": "Popular '50s kids' show that featured the clown seen here(\"Clarabell\")"}, {"answer": ["Clown Hall of Fame"], "question": "In 1994 Annie Fratellini became the first woman inducted into this Wisconsin site"}, {"answer": ["Pies"], "question": "(Bozo the Clown speaking)  In October 1998 a big rig hauling 10 tons of these overturned on an L.A. freeway; Soupy Sales wasn't responsible (laughing)"}, {"answer": ["Shriners"], "question": "The ISCA is an association of this Masonic organization's clowns"}, {"answer": ["Ronald McDonald"], "question": "This clown stars in the animated video \"The Legend of Grimace Island\""}]}
{"category": "A LITTLE GAME OF CARDS?", "comments": "", "clues": [{"answer": ["Solitaire"], "question": "Wes Cherry developed the version of this card game for one that came with Windows 95"}, {"answer": ["Pinochle"], "question": "Put on your glasses to play this 48-card game; its name is from binocle, \"pince-nez\""}, {"answer": ["Slapjack"], "question": "Fun for all ages, it's the game demonstrated here"}, {"answer": ["4"], "question": "In the game of authors, it takes this many cards to form a \"book\""}, {"answer": ["Shoe"], "question": "In Vegas casinos the 8 decks used to play baccarat are held in & dealt from a really big one of these"}]}
{"category": "BREAKFAST MENU", "comments": "", "clues": [{"answer": ["Prunes"], "question": "You might start off your meal with half a grapefruit or these dried plums stewed"}, {"answer": ["Eggos"], "question": "Tired of eating Special K from a bowl?  It also comes in the form of these round waffles from Kellogg's"}, {"answer": ["Hollandaise sauce"], "question": "Like Eggs Benedict, Eggs Sardou is topped with this creamy sauce"}, {"answer": ["Grits"], "question": "Craig Claiborne says, \"Breakfast in the South without\" this side dish \"borders on the unthinkable\""}, {"answer": ["Frittata"], "question": "Often cooked with vegetables & served open-faced, it's the Italian version of an omelet"}]}
{"category": "BIRD WORDS & PHRASES", "comments": "", "clues": [{"answer": ["The worm"], "question": "Many a slugabed has been reminded that \"The early bird catches\" this"}, {"answer": ["Cockpit"], "question": "Originally a place in which fowl fought, it now often refers to the pilot's compartment in an airplane"}, {"answer": ["Crow"], "question": "When forced to admit a mistake, you have to \"eat\" this bird (which is far from appetizing)"}, {"answer": ["Jaybird"], "question": "If you're completely undressed, you're as \"naked as\" this bird that's noisy & often bright blue"}, {"answer": ["Killing two birds with one stone"], "question": "It's a \"homicidal\" phrase for achieving 2 goals with a single effort"}]}
{"category": "CONTEMPORARY AUTHORS", "comments": "", "clues": [{"answer": ["Anne Rice"], "question": "Among the items that have been sold on her website are a Coven party fan & Lestat cologne & wine"}, {"answer": ["Fannie Flagg"], "question": "This comedienne's \"Fried Green Tomatoes at the Whistle Stop Cafe\" was inspired by her aunt's cafe in Alabama"}, {"answer": ["Erich Segal"], "question": "He gave us the line \"Love means never having to say you're sorry\""}, {"answer": ["Michael Crichton"], "question": "He published \"The Andromeda Strain\" in 1969, during his last year in medical school"}, {"answer": ["Mary Higgins Clark"], "question": "Several of her suspense novels including \"Let Me Call You Sweetheart\" derive their titles from old songs"}]}
{"category": "HISTORIC GEOGRAPHY", "comments": "", "clues": [{"answer": ["Cyprus"], "question": "Turkey invaded the northern part of this island nation in 1974"}, {"answer": ["Haiti"], "question": "After freeing it from France, Toussaint L'Ouverture became the first ruler of this nation"}, {"answer": ["Norway"], "question": "By 900 A.D. Harold Fairhair had become the first king of this Scandinavian nation"}, {"answer": ["United Arab Republic (UAR)"], "question": "Under the leadership of Nasser, this union of Egypt & Syria was proclaimed Feb. 1, 1958"}, {"answer": ["Ceylon (now Sri Lanka)"], "question": "Until 1972 this was the name of the Indian Ocean island whose current name means \"resplendent land\""}]}
{"category": "QUOTATIONS", "comments": "", "clues": [{"answer": ["Cape Cod"], "question": "Thoreau wrote that this \"is the bared and bended arm of Massachusetts: the shoulder is at Buzzards Bay\""}, {"answer": ["Boston Tea Party"], "question": "John Adams wrote of this 1773 event, \"There is a dignity, a majesty...in this last effort of the patriots that I greatly admire\""}, {"answer": ["Harry S. Truman (on the death of FDR)"], "question": "This American said of April 12, 1945, \"I felt like the moon and the stars and all the planets had fallen on me\""}, {"answer": ["Pablo Picasso"], "question": "This Spaniard's mom said if he were a monk, he'd wind up pope; he said, \"Instead, I became a painter & wound up as (me)\""}, {"answer": ["Voltaire"], "question": "Wordsworth called this author's \"Candide\" a \"dull product of a scoffer's pen\""}]}
{"category": "THE CINEMA", "comments": "", "clues": [{"answer": ["Rambo"], "question": "Stallone's 3-movie Vietnam vet"}, {"answer": ["Ingrid Bergman"], "question": "This actress gave birth to Robertino Rossellini in 1950"}, {"answer": ["1941"], "question": "\"How Green Was My Valley\" won a Best Picture Oscar for this year, the same year \"Citizen Kane\" was released"}, {"answer": ["Nosferatu"], "question": "Klaus Kinski played this title sucker in 1979; Max Schreck played him in 1922"}, {"answer": ["Ernst Stavro Blofeld"], "question": "Donald Pleasance & Charles Gray have both portrayed this diabolical James Bond nemesis"}]}
{"category": "THE CIVIL WAR", "comments": "", "clues": [{"answer": ["Richmond"], "question": "After this city fell April 2, 1865, federal troops placed a Union flag on top of the Confederate capitol"}, {"answer": ["Frederick Douglass"], "question": "In 1863 Lincoln met with this orator who urged full equality for black troops"}, {"answer": ["J.E.B. Stuart"], "question": "This Confederate general with the given names James Ewell Brown was famous for his rides \"around McClellan\""}, {"answer": ["Georgia"], "question": "Ezra Church & Chickamauga were among the battles fought in this state"}, {"answer": ["Belle Boyd"], "question": "After moving to England, this Confederate spy married her former captor, lieutenant Sam Hardinge"}]}
{"category": "\"GRANT\"s & \"LEE\"s", "comments": "", "clues": [{"answer": ["Tommy Lee"], "question": "He was added & cut from Pamela Anderson's life"}, {"answer": ["Lee Trevino"], "question": "In the '70s this golfer's followers were known as his \"Fleas\""}, {"answer": ["Gypsy Rose Lee"], "question": "At an early age, she stripped herself of the name Rose Louise Hovick"}, {"answer": ["Grant Hill"], "question": "In a high-round draft choice in 1994, the Pistons picked up steam with the addition of this player"}, {"answer": ["Land grant colleges"], "question": "The bill creating these colleges was signed into law by Abraham Lincoln"}]}
