{"category": "VICE PRESIDENTS", "comments": "", "clues": [{"answer": ["Constitution"], "question": "Elbridge Gerry signed the Declaration of Independence but refused to sign this 1787 document"}, {"answer": ["Walter Mondale"], "question": "He was a protege of Hubert Humphrey & replaced Humphrey in the U.S. Senate"}, {"answer": ["Gerald Ford"], "question": "He was a boxing & football coach at Yale before attending law school there"}, {"answer": ["Charles Fairbanks"], "question": "This vice president for whom an Alaskan city is named was involved in Canadian-Alaskan border negotiations"}, {"answer": ["Alben Barkley"], "question": "He was Senate Majority Leader from 1937-1947 & vice president from 1949-1953"}]}
{"category": "PEOPLE", "comments": "", "clues": [{"answer": ["Tootsie Roll"], "question": "You could say Ellen Gordon's career is \"on a roll\"; she's president of this candy company"}, {"answer": ["Lee Iacocca"], "question": "In 1983 he said, \"We at Chrysler borrow money the old fashioned way: we pay it back\""}, {"answer": ["Akira Kurosawa"], "question": "This director of \"Seven Samurai\" is descended from the great 11th century samurai Abe Sadato"}, {"answer": ["Harry Reasoner"], "question": "This late \"60 Minutes\" reporter & ABC anchorman wrote a 1946 novel titled \"Tell Me About Women\""}, {"answer": ["John Paul II (Karol Wojtyla)"], "question": "At the age of 58, he became the youngest man elected pope in the 20th century"}]}
{"category": "SIGNS & SYMBOLS", "comments": "", "clues": [{"answer": ["Shamrock"], "question": "The name of this good luck symbol comes from an Irish word for \"little clover\""}, {"answer": ["Smokey the Bear"], "question": "This symbol of fire prevention first appeared on a 1944 poster"}, {"answer": ["Mega-"], "question": "Among metric prefix symbols are m for milli- & M, which stands for this"}, {"answer": ["Equal sign"], "question": "The sign for a doubled bond in chemistry resembles this sign in mathematics"}, {"answer": ["Breve"], "question": "The U-shaped line put over a vowel to indicate a short sound; its name is from Latin for \"short\""}]}
{"category": "HEMINGWAY BOOKS", "comments": "", "clues": [{"answer": ["\"The Old Man and the Sea\""], "question": "At the end of this 1952 novella, Manolin promises to accompany Santiago on future fishing trips"}, {"answer": ["Bullfighting"], "question": "Sport that's the subject of \"The Dangerous Summer\" as well as \"Death in the Afternoon\""}, {"answer": ["\"For Whom the Bell Tolls\""], "question": "The title of this novel of the Spanish Civil War comes from John Donne's \"Meditation XVII\""}, {"answer": ["\"Islands in the Stream\""], "question": "He drew on his World War II experience looking for German submarines for this novel published in 1970"}, {"answer": ["\"A Farewell to Arms\""], "question": "Lt. Frederic Henry leaves the Italian army & flees to Switzerland with Catherine in this novel"}]}
{"category": "COMMON BONDS", "comments": "", "clues": [{"answer": ["Cards"], "question": "Playing,tarot,greeting"}, {"answer": ["Glass"], "question": "Sandwich,stained,Steuben"}, {"answer": ["Seats"], "question": "Love,hot,rumble"}, {"answer": ["Bats"], "question": "Baseball,cricket,vampire"}, {"answer": ["Maids"], "question": "Milk,meter,Marian"}]}
{"category": "\"A\" IN GEOGRAPHY", "comments": "", "clues": [{"answer": ["Avon"], "question": "Several English rivers bear this name; the one associated with Shakespeare rises in Northamptonshire"}, {"answer": ["Argentina"], "question": "There's a Liberty cap on the coat of arms of this South American country"}, {"answer": ["Arabian Sea"], "question": "The Gulf of Oman is an arm of this sea"}, {"answer": ["Angola"], "question": "It was once known as Portuguese West Africa"}, {"answer": ["Adelaide"], "question": "This capital of South Australia was named for the wife of King William IV"}]}
{"category": "THE 17th CENTURY", "comments": "", "clues": [{"answer": ["Athens"], "question": "In 1687, the Parthenon was badly damaged when the Venetians tried to conquer this city"}, {"answer": ["Galileo"], "question": "In 1610 Cosimo de Medici made this astronomer his court mathematician"}, {"answer": ["Dutch East India Company"], "question": "In 1610 this Dutch firm shipped tea from China to Europe for the first time"}, {"answer": ["Kingston"], "question": "This Jamaican city was founded around 1693 after an earthquake destroyed Port Royal across the harbor"}, {"answer": ["Russia"], "question": "The 1689 Treaty of Nerchinsk fixed China's border with this country along the Amur River valley"}]}
{"category": "THE AMERICAN FLAG", "comments": "", "clues": [{"answer": ["Memorial Day"], "question": "On this holiday, the flag flies at half-staff from sunrise to noon, & at full-staff from noon to sunset"}, {"answer": ["Antarctica"], "question": "The U.S. flag first flew on this continent in 1840 during the Charles Wilkes expedition"}, {"answer": ["Republic"], "question": "According to the Pledge of Allegiance, the American flag stands for this type of government"}, {"answer": ["Fort McHenry"], "question": "Mary Pickersgill of Baltimore, Maryland made the flag that flew on this site in September of 1814"}, {"answer": ["Marquis de Lafayette"], "question": "By custom, the U.S. flag flies over his tomb in Paris"}]}
{"category": "MUSIC APPRECIATION", "comments": "", "clues": [{"answer": ["Benny Goodman"], "question": "In 1948 Aaron Copland wrote a clarinet concerto for this swing band leader & clarinetist"}, {"answer": ["Violin"], "question": "Based on the tune \"O Mama Mia\", Paganini's \"Carnival of Venice\" is written for piano & this instrument"}, {"answer": ["Franz Joseph Haydn"], "question": "His great 1798 oratorio \"The Creation\" is known in German as \"Die Schopfung\""}, {"answer": ["Esa-Pekka Salonen"], "question": "In 1992 this Finnish conductor became director of the Los Angeles Philharmonic"}, {"answer": ["Carlos Montoya"], "question": "Born in 1903, this Spaniard was the first flamenco guitarist to perform as a soloist without dancers"}]}
{"category": "FINANCE", "comments": "", "clues": [{"answer": ["Gross National Product"], "question": "A basic indicator of a nation's economic strength is the GNP, which stands for this"}, {"answer": ["Penny stock"], "question": "It's the term for an often speculative security that typically sells for less than a dollar"}, {"answer": ["401K plan"], "question": "In 1994 the maximum employees could contribute to this pension plan was $9,240"}, {"answer": ["Food"], "question": "According to Engel's Law, when the income of a household rises, the percentage spent on this decreases"}, {"answer": ["Truth in Lending Act"], "question": "This 1968 act gave consumers the right to know the total costs & conditions before borrowing money"}]}
{"category": "ART", "comments": "", "clues": [{"answer": ["Leonardo da Vinci"], "question": "For his mural \"The Last Supper\", he used oils instead of the watercolors of normal frescoes"}, {"answer": ["Mosaics"], "question": "The floor type of this art form originated with pebble floors laid in late-Neolithic Crete"}, {"answer": ["Toulouse-Lautrec"], "question": "In 1892 this French artist portrayed dancer La Goulue entering the Moulin Rouge"}, {"answer": ["Grant Wood"], "question": "This \"American Gothic\" painter operated the Stone City Art Colony to help younger artists"}, {"answer": ["Titian"], "question": "In 1543 this Venetian traveled to Bologna to paint the portrait \"Pope Paul III Without Cap\""}]}
{"category": "BIBLES", "comments": "(Alex: And finally, a whole category devoted to...)", "clues": [{"answer": ["Verses"], "question": "The Geneva Bible of 1560 was the first English Bible in which the chapters were divided into these"}, {"answer": ["Seventh (\"Thou shalt not commit adultery\")"], "question": "London printers of a 1631 Bible were fined 300 pounds for leaving the word \"not\" out of this fidelity commandment"}, {"answer": ["Greek"], "question": "The Septuagint is the oldest translation of the Old Testament from Hebrew to this language"}, {"answer": ["Henry VIII"], "question": "The Cranmer Bible of 1540 featured a Holbein woodcut of this king watching copies being passed out"}, {"answer": ["Vulgate"], "question": "It's the name given to the Latin version of the Bible authorized by the Roman Catholic Church"}]}
